README.rst
setup.cfg
setup.py
pyexperiment/Config.py
pyexperiment/Logger.py
pyexperiment/State.py
pyexperiment/__init__.py
pyexperiment/experiment.py
pyexperiment/replicate.py
pyexperiment/state_context.py
pyexperiment/version.py
pyexperiment.egg-info/PKG-INFO
pyexperiment.egg-info/SOURCES.txt
pyexperiment.egg-info/dependency_links.txt
pyexperiment.egg-info/pbr.json
pyexperiment.egg-info/requires.txt
pyexperiment.egg-info/top_level.txt
pyexperiment/utils/DelegateCall.py
pyexperiment/utils/HierarchicalMapping.py
pyexperiment/utils/Singleton.py
pyexperiment/utils/__init__.py
pyexperiment/utils/config_conversion.py
pyexperiment/utils/functional.py
pyexperiment/utils/interactive.py
pyexperiment/utils/persistent_memoize.py
pyexperiment/utils/plot.py
pyexperiment/utils/printers.py
pyexperiment/utils/sentinel.py
pyexperiment/utils/stdout_redirector.py