Metadata-Version: 1.1
Name: pyexperiment
Version: 0.8.10
Summary: Run experiments with Python - quick and clean.
Home-page: https://github.com/duerrp/pyexperiment
Author: Peter Duerr
Author-email: duerrp@gmail.com
License: MIT
Keywords: science experiment
Platform: UNKNOWN
Classifier: Development Status :: 3 - Alpha
Classifier: Topic :: Utilities
Classifier: License :: OSI Approved :: MIT License
Classifier: Programming Language :: Python
Classifier: Programming Language :: Python :: 2.7
Classifier: Programming Language :: Python :: 3.2
Classifier: Programming Language :: Python :: 3.3
Classifier: Programming Language :: Python :: 3.4
Classifier: Programming Language :: Python :: Implementation :: CPython
